api_v1/__init__.py
api_v1/admin.py
api_v1/apps.py
api_v1/permissions.py
api_v1/serializers/__init__.py
api_v1/serializers/autor.py
api_v1/serializers/nagroda.py
api_v1/serializers/openaccess.py
api_v1/serializers/patent.py
api_v1/serializers/praca_doktorska.py
api_v1/serializers/praca_habilitacyjna.py
api_v1/serializers/raport_slotow_uczelnia.py
api_v1/serializers/struktura.py
api_v1/serializers/system.py
api_v1/serializers/util.py
api_v1/serializers/wydawca.py
api_v1/serializers/wydawnictwo_ciagle.py
api_v1/serializers/wydawnictwo_zwarte.py
api_v1/serializers/zrodlo.py
api_v1/urls.py
api_v1/views.py
api_v1/viewsets/__init__.py
api_v1/viewsets/autor.py
api_v1/viewsets/common.py
api_v1/viewsets/nagroda.py
api_v1/viewsets/openaccess.py
api_v1/viewsets/patent.py
api_v1/viewsets/praca_doktorska.py
api_v1/viewsets/praca_habilitacyjna.py
api_v1/viewsets/raport_slotow_uczelnia.py
api_v1/viewsets/struktura.py
api_v1/viewsets/system.py
api_v1/viewsets/wydawca.py
api_v1/viewsets/wydawnictwo_ciagle.py
api_v1/viewsets/wydawnictwo_zwarte.py
api_v1/viewsets/zrodlo.py
bpp/__init__.py
bpp/admin/__init__.py
bpp/admin/actions.py
bpp/admin/autor.py
bpp/admin/autor_dyscyplina.py
bpp/admin/bppmultiseekvisibility.py
bpp/admin/charakter_formalny.py
bpp/admin/core.py
bpp/admin/crossref_api_helpers.py
bpp/admin/dyscyplina_naukowa.py
bpp/admin/element_repozytorium.py
bpp/admin/filters.py
bpp/admin/grant.py
bpp/admin/helpers/__init__.py
bpp/admin/helpers/fieldsets.py
bpp/admin/helpers/mixins.py
bpp/admin/helpers/pbn_api/__init__.py
bpp/admin/helpers/pbn_api/cli.py
bpp/admin/helpers/pbn_api/common.py
bpp/admin/helpers/pbn_api/gui.py
bpp/admin/helpers/widgets.py
bpp/admin/jednostka.py
bpp/admin/kierunek_studiow.py
bpp/admin/konferencja.py
bpp/admin/nagroda.py
bpp/admin/patent.py
bpp/admin/praca_doktorska.py
bpp/admin/praca_habilitacyjna.py
bpp/admin/seria_wydawnicza.py
bpp/admin/szablondlaopisubibliograficznego.py
bpp/admin/templates.py
bpp/admin/uczelnia.py
bpp/admin/wydawca.py
bpp_iplweb-202504.1174.dist-info/AUTHORS.rst
bpp_iplweb-202504.1174.dist-info/LICENSE
bpp_iplweb-202504.1174.dist-info/METADATA
bpp_iplweb-202504.1174.dist-info/WHEEL
bpp_iplweb-202504.1174.dist-info/entry_points.txt
bpp_iplweb-202504.1174.dist-info/RECORD
