Metadata-Version: 2.3
Name: bpp_iplweb
Version: 202504.1174
Summary: 
License: MIT
Author: Michał Pasternak
Author-email: michal.dtz@gmail.com
Requires-Python: >=3.10,<3.12
Classifier: License :: OSI Approved :: MIT License
Classifier: Programming Language :: Python :: 3
Classifier: Programming Language :: Python :: 3.10
Classifier: Programming Language :: Python :: 3.11
Provides-Extra: ldap
Provides-Extra: office365
Requires-Dist: Django (>=4.2,<4.3)
Requires-Dist: MOAI-iplweb (==2.0.0)
Requires-Dist: Markdown (==3.2.1)
Requires-Dist: Pillow (>=10,<11)
Requires-Dist: Unidecode (==0.4.20)
Requires-Dist: arrow (==1.2.1)
Requires-Dist: bleach (>=3.3.0)
Requires-Dist: celery[redis] (==5.4.0)
Requires-Dist: channels-redis (>=4,<5)
Requires-Dist: channels[daphne] (>=4,<5)
Requires-Dist: chardet (>=5.2.0,<6.0.0)
Requires-Dist: crispy-bootstrap3 (>=2022.1,<2023.0)
Requires-Dist: crispy-bootstrap5 (>=0.7,<0.8)
Requires-Dist: crispy-forms-foundation (==1.0.1)
Requires-Dist: crossrefapi (>=1.6.0,<2.0.0)
Requires-Dist: cssmin (==0.2.0)
Requires-Dist: dbfread (>=2.0.7,<3.0.0)
Requires-Dist: dj-pagination (==2.4.0)
Requires-Dist: django-admin-sortable2 (>=2,<3)
Requires-Dist: django-admin-tools (==0.9.2)
Requires-Dist: django-auth-ldap (>=4.1.0,<5.0.0) ; extra == "ldap"
Requires-Dist: django-autocomplete-light (==3.9.4)
Requires-Dist: django-autoslug (==1.9.8)
Requires-Dist: django-braces (>=1.15.0,<2.0.0)
Requires-Dist: django-cacheops (==7.0.2)
Requires-Dist: django-celery-email (>=3.0.0,<4.0.0)
Requires-Dist: django-celery-results (==2.4.0)
Requires-Dist: django-classy-tags (==4.0.0)
Requires-Dist: django-columns (==0.1.0)
Requires-Dist: django-compressor (==4.4)
Requires-Dist: django-cookie-law (==2.2.0)
Requires-Dist: django-crispy-forms (==2.0.0)
Requires-Dist: django-dbtemplates (>=4.0,<5.0)
Requires-Dist: django-denorm-iplweb (>=1.1.3,<2.0.0)
Requires-Dist: django-dirtyfields (==1.3.1)
Requires-Dist: django-easy-audit (>=1.3.3,<2.0.0)
Requires-Dist: django-environ (>=0.9.0,<0.10.0)
Requires-Dist: django-extensions (==3.1.3)
Requires-Dist: django-favicon-plus-reloaded (==1.1.6)
Requires-Dist: django-filter (==21.1)
Requires-Dist: django-flexible-reports (>0.2.9)
Requires-Dist: django-formtools (==2.3)
Requires-Dist: django-fsm (==2.8.0)
Requires-Dist: django-grappelli (==3.0.6)
Requires-Dist: django-group-by (==0.3.1)
Requires-Dist: django-htmlmin (==0.11.0)
Requires-Dist: django-import-export (==3.2.0)
Requires-Dist: django-loginas (==0.3.11)
Requires-Dist: django-messages-extends (==0.6.3)
Requires-Dist: django-microsoft-auth (>=3.0.1,<4.0.0) ; extra == "office365"
Requires-Dist: django-model-utils (==4.3.1)
Requires-Dist: django-mptt (==0.13.4)
Requires-Dist: django-multiseek (==0.9.47)
Requires-Dist: django-password-policies-iplweb (==0.8.5)
Requires-Dist: django-querysetsequence (==0.12)
Requires-Dist: django-reversion (==5.0.4)
Requires-Dist: django-robots (==5.0)
Requires-Dist: django-sendfile2 (==0.7.0)
Requires-Dist: django-session-security (==2.6.7)
Requires-Dist: django-soft-delete (>=1.0.15,<2.0.0)
Requires-Dist: django-static-sitemaps (>=5.0.0,<6.0.0)
Requires-Dist: django-tables2 (==2.3.1)
Requires-Dist: django-tabular-permissions (==2.9.1)
Requires-Dist: django-taggit (==4.0.0)
Requires-Dist: django-templated-email (>=3.0.0,<4.0.0)
Requires-Dist: django-tinymce (>=3.6.1,<4.0.0)
Requires-Dist: django-weasyprint (>=2.1.0,<3.0.0)
Requires-Dist: django-webmaster-verification (==0.4.3)
Requires-Dist: django_redis (==5.3.0)
Requires-Dist: djangoql (==0.17.1)
Requires-Dist: djangorestframework (==3.14.0)
Requires-Dist: isbnlib (>=3.10.14,<4.0.0)
Requires-Dist: numpy (>=2.1.2,<3.0.0)
Requires-Dist: olefile (==0.44)
Requires-Dist: openpyxl (>=3.1.5,<4.0.0)
Requires-Dist: pandas (>=2.2.3,<3.0.0)
Requires-Dist: pathspec (>=0.9.0,<0.10.0)
Requires-Dist: progressbar2 (>=4.0.0,<5.0.0)
Requires-Dist: psycopg2 (>=2.9.9,<3.0.0)
Requires-Dist: pygad (>=3.3.1,<4.0.0)
Requires-Dist: pymed-iplweb (==0.8.10)
Requires-Dist: pyoai (==2.5.0)
Requires-Dist: pypandoc (==1.5)
Requires-Dist: python-dateutil (>=2.9.0.post0,<3.0.0)
Requires-Dist: requests (>=2.32.3,<3.0.0)
Requires-Dist: requests-oauthlib (==1.3.0)
Requires-Dist: rjsmin (==1.2.1)
Requires-Dist: sentry-sdk[django] (>=2.19.0,<3.0.0)
Requires-Dist: simplejson (==3.17.5)
Requires-Dist: tablib (==3.5.0)
Requires-Dist: tqdm (>=4.67.1,<5.0.0)
Requires-Dist: twisted[http2,tls] (>=24.3.0,<25.0.0)
Requires-Dist: uvicorn[standard] (>=0.31.0,<0.32.0)
Requires-Dist: weasyprint (==55.0)
Requires-Dist: wosclient (==0.1.5)
Requires-Dist: xlrd (==2.0.1)
